{
    "total_plays": 50,
    "tracks": [
        {
            "song_name": "Wish I Never Met You - Prison Tapes",
            "artists": [
                "Tory Lanez"
            ],
            "album": "Wish I Never Met You (Prison Tapes)",
            "played_at": "01/08/2024 - 17:58:02"
        },
        {
            "song_name": "Self Care",
            "artists": [
                "Mac Miller"
            ],
            "album": "Swimming",
            "played_at": "01/08/2024 - 17:54:17"
        },
        {
            "song_name": "A Keeper",
            "artists": [
                "Drake"
            ],
            "album": "Honestly, Nevermind",
            "played_at": "01/08/2024 - 17:48:32"
        },
        {
            "song_name": "Sudden Change",
            "artists": [
                "Lonely Joyman"
            ],
            "album": "A Bit of Colour",
            "played_at": "01/08/2024 - 17:45:38"
        },
        {
            "song_name": "Dad's Typewriter Feels",
            "artists": [
                "Looper Boy"
            ],
            "album": "Once Again",
            "played_at": "01/08/2024 - 17:43:52"
        },
        {
            "song_name": "Dad's Typewriter Feels",
            "artists": [
                "Looper Boy"
            ],
            "album": "Once Again",
            "played_at": "01/08/2024 - 17:41:41"
        },
        {
            "song_name": "Boulevard",
            "artists": [
                "Jasper Nyx"
            ],
            "album": "Boulevard",
            "played_at": "01/08/2024 - 17:29:11"
        },
        {
            "song_name": "pawsitive",
            "artists": [
                "misty tapes"
            ],
            "album": "pawsitive",
            "played_at": "01/08/2024 - 17:26:26"
        },
        {
            "song_name": "Phunsmoke",
            "artists": [
                "LOFI FRAN"
            ],
            "album": "Phunsmoke",
            "played_at": "01/08/2024 - 17:24:15"
        },
        {
            "song_name": "Cruising",
            "artists": [
                "Lghtr"
            ],
            "album": "Cruising",
            "played_at": "01/08/2024 - 17:22:28"
        },
        {
            "song_name": "winter balloon",
            "artists": [
                "Ponzi Skeemz"
            ],
            "album": "winter balloon",
            "played_at": "01/08/2024 - 17:20:25"
        },
        {
            "song_name": "In Comparison With",
            "artists": [
                "State Artefact"
            ],
            "album": "In Comparison With",
            "played_at": "01/08/2024 - 17:18:19"
        },
        {
            "song_name": "Kalamos",
            "artists": [
                "Drips Zacheer",
                "Soulvibe Cuts"
            ],
            "album": "Kalamos",
            "played_at": "01/08/2024 - 17:15:03"
        },
        {
            "song_name": "Chewy",
            "artists": [
                "sloh rou",
                "ron quixote"
            ],
            "album": "Chewy",
            "played_at": "01/08/2024 - 17:13:01"
        },
        {
            "song_name": "Sundew",
            "artists": [
                "Sátyr",
                "Otaam",
                "Dubillard",
                "Enluv"
            ],
            "album": "Sundew",
            "played_at": "01/08/2024 - 17:10:38"
        },
        {
            "song_name": "Early Birds",
            "artists": [
                "FloFilz",
                "HNNY"
            ],
            "album": "Early Birds",
            "played_at": "01/08/2024 - 17:06:57"
        },
        {
            "song_name": "bahia nights",
            "artists": [
                "moodsinger"
            ],
            "album": "bahia nights",
            "played_at": "01/08/2024 - 17:04:41"
        },
        {
            "song_name": "same dream",
            "artists": [
                "sozin"
            ],
            "album": "same dream",
            "played_at": "01/08/2024 - 17:02:42"
        },
        {
            "song_name": "Sea Breeze",
            "artists": [
                "Shimon Hoshino"
            ],
            "album": "Sea Breeze",
            "played_at": "01/08/2024 - 17:00:26"
        },
        {
            "song_name": "Like a Mystery",
            "artists": [
                "Eneko Artola"
            ],
            "album": "Like a Mystery",
            "played_at": "01/08/2024 - 16:50:59"
        },
        {
            "song_name": "Sweetly",
            "artists": [
                "Honey",
                "Summer Vibes"
            ],
            "album": "Sweetly",
            "played_at": "01/08/2024 - 16:48:47"
        },
        {
            "song_name": "I Can't Stop",
            "artists": [
                "Daniel Glaven",
                "Will Church"
            ],
            "album": "I Can't Stop",
            "played_at": "01/08/2024 - 16:46:16"
        },
        {
            "song_name": "Love Me",
            "artists": [
                "Donner"
            ],
            "album": "Love Me",
            "played_at": "01/08/2024 - 16:44:10"
        },
        {
            "song_name": "Coming With You",
            "artists": [
                "Horizon Blue",
                "Felix Samuel"
            ],
            "album": "Coming With You",
            "played_at": "01/08/2024 - 16:42:02"
        },
        {
            "song_name": "Dreams",
            "artists": [
                "Kenn Colt",
                "Adam Pickard"
            ],
            "album": "BALANCE",
            "played_at": "01/08/2024 - 16:39:49"
        },
        {
            "song_name": "Covered By The Clouds",
            "artists": [
                "NSH"
            ],
            "album": "Covered By The Clouds",
            "played_at": "01/08/2024 - 16:36:32"
        },
        {
            "song_name": "Talking To Myself",
            "artists": [
                "Namic",
                "Meynberg"
            ],
            "album": "Talking To Myself",
            "played_at": "01/08/2024 - 16:33:19"
        },
        {
            "song_name": "King",
            "artists": [
                "TWOPILOTS"
            ],
            "album": "King",
            "played_at": "01/08/2024 - 16:31:14"
        },
        {
            "song_name": "high love",
            "artists": [
                "rayn",
                "cloudseven",
                "MELINA"
            ],
            "album": "high love",
            "played_at": "01/08/2024 - 16:27:50"
        },
        {
            "song_name": "17",
            "artists": [
                "Weisser Quiff"
            ],
            "album": "17",
            "played_at": "01/08/2024 - 16:25:23"
        },
        {
            "song_name": "Dollar Dream [Lucas Estrada Edit]",
            "artists": [
                "Lucas Estrada",
                "Couché",
                "Polar Notes",
                "Mentum"
            ],
            "album": "Dollar Dream [Lucas Estrada Edit]",
            "played_at": "01/08/2024 - 16:22:36"
        },
        {
            "song_name": "Hollywood",
            "artists": [
                "Natio",
                "Nina Carr"
            ],
            "album": "Hollywood",
            "played_at": "01/08/2024 - 16:20:04"
        },
        {
            "song_name": "Stop Us Now",
            "artists": [
                "NSH",
                "DT James"
            ],
            "album": "Stop Us Now",
            "played_at": "01/08/2024 - 16:17:39"
        },
        {
            "song_name": "Sunset Lovers",
            "artists": [
                "Thierry Von Der Warth",
                "Horizon Blue",
                "Carston"
            ],
            "album": "Sunset Lovers",
            "played_at": "01/08/2024 - 16:15:31"
        },
        {
            "song_name": "Cool Kids",
            "artists": [
                "Toby Rose",
                "TWOPILOTS"
            ],
            "album": "Cool Kids",
            "played_at": "01/08/2024 - 16:12:41"
        },
        {
            "song_name": "In Too Deep",
            "artists": [
                "WEEKLESS",
                "WEDONT",
                "ROBINS"
            ],
            "album": "In Too Deep",
            "played_at": "01/08/2024 - 16:10:14"
        },
        {
            "song_name": "Over You",
            "artists": [
                "Madism",
                "Philip Strand"
            ],
            "album": "Over You",
            "played_at": "01/08/2024 - 16:07:35"
        },
        {
            "song_name": "Moonlight",
            "artists": [
                "Thunder"
            ],
            "album": "Moonlight",
            "played_at": "01/08/2024 - 16:05:19"
        },
        {
            "song_name": "Fallin' In Love",
            "artists": [
                "Ruxolf",
                "Marphil"
            ],
            "album": "Fallin' In Love",
            "played_at": "01/08/2024 - 16:03:17"
        },
        {
            "song_name": "Fire in the Sky",
            "artists": [
                "Roman Müller",
                "Clay Pirinha"
            ],
            "album": "Fire in the Sky",
            "played_at": "01/08/2024 - 16:00:45"
        },
        {
            "song_name": "Sunbeams",
            "artists": [
                "NSH"
            ],
            "album": "Sunbeams",
            "played_at": "01/08/2024 - 15:57:55"
        },
        {
            "song_name": "Guy For That (Feat. Luke Combs)",
            "artists": [
                "Post Malone",
                "Luke Combs"
            ],
            "album": "Guy For That",
            "played_at": "01/08/2024 - 15:54:03"
        },
        {
            "song_name": "Ball W/O You - Instrumental",
            "artists": [
                "DJ Glacier"
            ],
            "album": "Ball W/O You (Instrumental)",
            "played_at": "01/08/2024 - 15:52:05"
        },
        {
            "song_name": "Solo - Sped Up + Instrumental",
            "artists": [
                "dopuu"
            ],
            "album": "Solo - Sped Up + Instrumental",
            "played_at": "01/08/2024 - 15:48:50"
        },
        {
            "song_name": "Dreams",
            "artists": [
                "DJ ZeeZee"
            ],
            "album": "Dreams",
            "played_at": "01/08/2024 - 15:44:46"
        },
        {
            "song_name": "Let Go",
            "artists": [
                "Ark Patrol",
                "Veronika Redd"
            ],
            "album": "Let Go (Acoustic)",
            "played_at": "01/08/2024 - 15:41:03"
        },
        {
            "song_name": "Silver Moon",
            "artists": [
                "Two Scents",
                "Mondo Loops"
            ],
            "album": "Lately",
            "played_at": "01/08/2024 - 15:36:55"
        },
        {
            "song_name": "Before It's Too Late",
            "artists": [
                "Kasper Lindmark"
            ],
            "album": "While You Were Away",
            "played_at": "01/08/2024 - 15:34:51"
        },
        {
            "song_name": "Spaghetti from the island",
            "artists": [
                "Slumberville"
            ],
            "album": "Liberation",
            "played_at": "01/08/2024 - 15:33:51"
        },
        {
            "song_name": "Bliss",
            "artists": [
                "Slumberville"
            ],
            "album": "Bliss",
            "played_at": "01/08/2024 - 15:32:06"
        },
        {
            "song_name": "Unforgettable",
            "artists": [
                "French Montana",
                "Swae Lee"
            ],
            "album": "Jungle Rules",
            "played_at": "01/08/2024 - 18:09:41"
        },
        {
            "song_name": "The Percocet & Stripper Joint",
            "artists": [
                "Future"
            ],
            "album": "DS2 (Deluxe)",
            "played_at": "01/08/2024 - 18:05:47"
        },
        {
            "song_name": "Ric Flair Drip (with Metro Boomin)",
            "artists": [
                "Offset",
                "Metro Boomin"
            ],
            "album": "Without Warning",
            "played_at": "01/08/2024 - 18:03:18"
        },
        {
            "song_name": "one of wun",
            "artists": [
                "Gunna"
            ],
            "album": "One of Wun",
            "played_at": "01/08/2024 - 18:00:26"
        },
        {
            "song_name": "Wish I Never Met You - Prison Tapes",
            "artists": [
                "Tory Lanez"
            ],
            "album": "Wish I Never Met You (Prison Tapes)",
            "played_at": "01/08/2024 - 17:58:02"
        },
        {
            "song_name": "Self Care",
            "artists": [
                "Mac Miller"
            ],
            "album": "Swimming",
            "played_at": "01/08/2024 - 17:54:17"
        },
        {
            "song_name": "A Keeper",
            "artists": [
                "Drake"
            ],
            "album": "Honestly, Nevermind",
            "played_at": "01/08/2024 - 17:48:32"
        },
        {
            "song_name": "Sudden Change",
            "artists": [
                "Lonely Joyman"
            ],
            "album": "A Bit of Colour",
            "played_at": "01/08/2024 - 17:45:38"
        },
        {
            "song_name": "Dad's Typewriter Feels",
            "artists": [
                "Looper Boy"
            ],
            "album": "Once Again",
            "played_at": "01/08/2024 - 17:43:52"
        },
        {
            "song_name": "Dad's Typewriter Feels",
            "artists": [
                "Looper Boy"
            ],
            "album": "Once Again",
            "played_at": "01/08/2024 - 17:41:41"
        },
        {
            "song_name": "Boulevard",
            "artists": [
                "Jasper Nyx"
            ],
            "album": "Boulevard",
            "played_at": "01/08/2024 - 17:29:11"
        },
        {
            "song_name": "pawsitive",
            "artists": [
                "misty tapes"
            ],
            "album": "pawsitive",
            "played_at": "01/08/2024 - 17:26:26"
        },
        {
            "song_name": "Phunsmoke",
            "artists": [
                "LOFI FRAN"
            ],
            "album": "Phunsmoke",
            "played_at": "01/08/2024 - 17:24:15"
        },
        {
            "song_name": "Cruising",
            "artists": [
                "Lghtr"
            ],
            "album": "Cruising",
            "played_at": "01/08/2024 - 17:22:28"
        },
        {
            "song_name": "winter balloon",
            "artists": [
                "Ponzi Skeemz"
            ],
            "album": "winter balloon",
            "played_at": "01/08/2024 - 17:20:25"
        },
        {
            "song_name": "In Comparison With",
            "artists": [
                "State Artefact"
            ],
            "album": "In Comparison With",
            "played_at": "01/08/2024 - 17:18:19"
        },
        {
            "song_name": "Kalamos",
            "artists": [
                "Drips Zacheer",
                "Soulvibe Cuts"
            ],
            "album": "Kalamos",
            "played_at": "01/08/2024 - 17:15:03"
        },
        {
            "song_name": "Chewy",
            "artists": [
                "sloh rou",
                "ron quixote"
            ],
            "album": "Chewy",
            "played_at": "01/08/2024 - 17:13:01"
        },
        {
            "song_name": "Sundew",
            "artists": [
                "Sátyr",
                "Otaam",
                "Dubillard",
                "Enluv"
            ],
            "album": "Sundew",
            "played_at": "01/08/2024 - 17:10:38"
        },
        {
            "song_name": "Early Birds",
            "artists": [
                "FloFilz",
                "HNNY"
            ],
            "album": "Early Birds",
            "played_at": "01/08/2024 - 17:06:57"
        },
        {
            "song_name": "bahia nights",
            "artists": [
                "moodsinger"
            ],
            "album": "bahia nights",
            "played_at": "01/08/2024 - 17:04:41"
        },
        {
            "song_name": "same dream",
            "artists": [
                "sozin"
            ],
            "album": "same dream",
            "played_at": "01/08/2024 - 17:02:42"
        },
        {
            "song_name": "Sea Breeze",
            "artists": [
                "Shimon Hoshino"
            ],
            "album": "Sea Breeze",
            "played_at": "01/08/2024 - 17:00:26"
        },
        {
            "song_name": "Like a Mystery",
            "artists": [
                "Eneko Artola"
            ],
            "album": "Like a Mystery",
            "played_at": "01/08/2024 - 16:50:59"
        },
        {
            "song_name": "Sweetly",
            "artists": [
                "Honey",
                "Summer Vibes"
            ],
            "album": "Sweetly",
            "played_at": "01/08/2024 - 16:48:47"
        },
        {
            "song_name": "I Can't Stop",
            "artists": [
                "Daniel Glaven",
                "Will Church"
            ],
            "album": "I Can't Stop",
            "played_at": "01/08/2024 - 16:46:16"
        },
        {
            "song_name": "Love Me",
            "artists": [
                "Donner"
            ],
            "album": "Love Me",
            "played_at": "01/08/2024 - 16:44:10"
        },
        {
            "song_name": "Coming With You",
            "artists": [
                "Horizon Blue",
                "Felix Samuel"
            ],
            "album": "Coming With You",
            "played_at": "01/08/2024 - 16:42:02"
        },
        {
            "song_name": "Dreams",
            "artists": [
                "Kenn Colt",
                "Adam Pickard"
            ],
            "album": "BALANCE",
            "played_at": "01/08/2024 - 16:39:49"
        },
        {
            "song_name": "Covered By The Clouds",
            "artists": [
                "NSH"
            ],
            "album": "Covered By The Clouds",
            "played_at": "01/08/2024 - 16:36:32"
        },
        {
            "song_name": "Talking To Myself",
            "artists": [
                "Namic",
                "Meynberg"
            ],
            "album": "Talking To Myself",
            "played_at": "01/08/2024 - 16:33:19"
        },
        {
            "song_name": "King",
            "artists": [
                "TWOPILOTS"
            ],
            "album": "King",
            "played_at": "01/08/2024 - 16:31:14"
        },
        {
            "song_name": "high love",
            "artists": [
                "rayn",
                "cloudseven",
                "MELINA"
            ],
            "album": "high love",
            "played_at": "01/08/2024 - 16:27:50"
        },
        {
            "song_name": "17",
            "artists": [
                "Weisser Quiff"
            ],
            "album": "17",
            "played_at": "01/08/2024 - 16:25:23"
        },
        {
            "song_name": "Dollar Dream [Lucas Estrada Edit]",
            "artists": [
                "Lucas Estrada",
                "Couché",
                "Polar Notes",
                "Mentum"
            ],
            "album": "Dollar Dream [Lucas Estrada Edit]",
            "played_at": "01/08/2024 - 16:22:36"
        },
        {
            "song_name": "Hollywood",
            "artists": [
                "Natio",
                "Nina Carr"
            ],
            "album": "Hollywood",
            "played_at": "01/08/2024 - 16:20:04"
        },
        {
            "song_name": "Stop Us Now",
            "artists": [
                "NSH",
                "DT James"
            ],
            "album": "Stop Us Now",
            "played_at": "01/08/2024 - 16:17:39"
        },
        {
            "song_name": "Sunset Lovers",
            "artists": [
                "Thierry Von Der Warth",
                "Horizon Blue",
                "Carston"
            ],
            "album": "Sunset Lovers",
            "played_at": "01/08/2024 - 16:15:31"
        },
        {
            "song_name": "Cool Kids",
            "artists": [
                "Toby Rose",
                "TWOPILOTS"
            ],
            "album": "Cool Kids",
            "played_at": "01/08/2024 - 16:12:41"
        },
        {
            "song_name": "In Too Deep",
            "artists": [
                "WEEKLESS",
                "WEDONT",
                "ROBINS"
            ],
            "album": "In Too Deep",
            "played_at": "01/08/2024 - 16:10:14"
        },
        {
            "song_name": "Over You",
            "artists": [
                "Madism",
                "Philip Strand"
            ],
            "album": "Over You",
            "played_at": "01/08/2024 - 16:07:35"
        },
        {
            "song_name": "Moonlight",
            "artists": [
                "Thunder"
            ],
            "album": "Moonlight",
            "played_at": "01/08/2024 - 16:05:19"
        },
        {
            "song_name": "Fallin' In Love",
            "artists": [
                "Ruxolf",
                "Marphil"
            ],
            "album": "Fallin' In Love",
            "played_at": "01/08/2024 - 16:03:17"
        },
        {
            "song_name": "Fire in the Sky",
            "artists": [
                "Roman Müller",
                "Clay Pirinha"
            ],
            "album": "Fire in the Sky",
            "played_at": "01/08/2024 - 16:00:45"
        },
        {
            "song_name": "Sunbeams",
            "artists": [
                "NSH"
            ],
            "album": "Sunbeams",
            "played_at": "01/08/2024 - 15:57:55"
        },
        {
            "song_name": "Guy For That (Feat. Luke Combs)",
            "artists": [
                "Post Malone",
                "Luke Combs"
            ],
            "album": "Guy For That",
            "played_at": "01/08/2024 - 15:54:03"
        },
        {
            "song_name": "Ball W/O You - Instrumental",
            "artists": [
                "DJ Glacier"
            ],
            "album": "Ball W/O You (Instrumental)",
            "played_at": "01/08/2024 - 15:52:05"
        },
        {
            "song_name": "Solo - Sped Up + Instrumental",
            "artists": [
                "dopuu"
            ],
            "album": "Solo - Sped Up + Instrumental",
            "played_at": "01/08/2024 - 15:48:50"
        },
        {
            "song_name": "Dreams",
            "artists": [
                "DJ ZeeZee"
            ],
            "album": "Dreams",
            "played_at": "01/08/2024 - 15:44:46"
        },
        {
            "song_name": "Let Go",
            "artists": [
                "Ark Patrol",
                "Veronika Redd"
            ],
            "album": "Let Go (Acoustic)",
            "played_at": "01/08/2024 - 15:41:03"
        },
        {
            "song_name": "Hate It Or Love It",
            "artists": [
                "The Game",
                "50 Cent"
            ],
            "album": "The Documentary",
            "played_at": "01/08/2024 - 18:10:12"
        },
        {
            "song_name": "Unforgettable",
            "artists": [
                "French Montana",
                "Swae Lee"
            ],
            "album": "Jungle Rules",
            "played_at": "01/08/2024 - 18:09:41"
        },
        {
            "song_name": "The Percocet & Stripper Joint",
            "artists": [
                "Future"
            ],
            "album": "DS2 (Deluxe)",
            "played_at": "01/08/2024 - 18:05:47"
        },
        {
            "song_name": "Ric Flair Drip (with Metro Boomin)",
            "artists": [
                "Offset",
                "Metro Boomin"
            ],
            "album": "Without Warning",
            "played_at": "01/08/2024 - 18:03:18"
        },
        {
            "song_name": "one of wun",
            "artists": [
                "Gunna"
            ],
            "album": "One of Wun",
            "played_at": "01/08/2024 - 18:00:26"
        },
        {
            "song_name": "Wish I Never Met You - Prison Tapes",
            "artists": [
                "Tory Lanez"
            ],
            "album": "Wish I Never Met You (Prison Tapes)",
            "played_at": "01/08/2024 - 17:58:02"
        },
        {
            "song_name": "Self Care",
            "artists": [
                "Mac Miller"
            ],
            "album": "Swimming",
            "played_at": "01/08/2024 - 17:54:17"
        },
        {
            "song_name": "A Keeper",
            "artists": [
                "Drake"
            ],
            "album": "Honestly, Nevermind",
            "played_at": "01/08/2024 - 17:48:32"
        },
        {
            "song_name": "Sudden Change",
            "artists": [
                "Lonely Joyman"
            ],
            "album": "A Bit of Colour",
            "played_at": "01/08/2024 - 17:45:38"
        },
        {
            "song_name": "Dad's Typewriter Feels",
            "artists": [
                "Looper Boy"
            ],
            "album": "Once Again",
            "played_at": "01/08/2024 - 17:43:52"
        },
        {
            "song_name": "Dad's Typewriter Feels",
            "artists": [
                "Looper Boy"
            ],
            "album": "Once Again",
            "played_at": "01/08/2024 - 17:41:41"
        },
        {
            "song_name": "Boulevard",
            "artists": [
                "Jasper Nyx"
            ],
            "album": "Boulevard",
            "played_at": "01/08/2024 - 17:29:11"
        },
        {
            "song_name": "pawsitive",
            "artists": [
                "misty tapes"
            ],
            "album": "pawsitive",
            "played_at": "01/08/2024 - 17:26:26"
        },
        {
            "song_name": "Phunsmoke",
            "artists": [
                "LOFI FRAN"
            ],
            "album": "Phunsmoke",
            "played_at": "01/08/2024 - 17:24:15"
        },
        {
            "song_name": "Cruising",
            "artists": [
                "Lghtr"
            ],
            "album": "Cruising",
            "played_at": "01/08/2024 - 17:22:28"
        },
        {
            "song_name": "winter balloon",
            "artists": [
                "Ponzi Skeemz"
            ],
            "album": "winter balloon",
            "played_at": "01/08/2024 - 17:20:25"
        },
        {
            "song_name": "In Comparison With",
            "artists": [
                "State Artefact"
            ],
            "album": "In Comparison With",
            "played_at": "01/08/2024 - 17:18:19"
        },
        {
            "song_name": "Kalamos",
            "artists": [
                "Drips Zacheer",
                "Soulvibe Cuts"
            ],
            "album": "Kalamos",
            "played_at": "01/08/2024 - 17:15:03"
        },
        {
            "song_name": "Chewy",
            "artists": [
                "sloh rou",
                "ron quixote"
            ],
            "album": "Chewy",
            "played_at": "01/08/2024 - 17:13:01"
        },
        {
            "song_name": "Sundew",
            "artists": [
                "Sátyr",
                "Otaam",
                "Dubillard",
                "Enluv"
            ],
            "album": "Sundew",
            "played_at": "01/08/2024 - 17:10:38"
        },
        {
            "song_name": "Early Birds",
            "artists": [
                "FloFilz",
                "HNNY"
            ],
            "album": "Early Birds",
            "played_at": "01/08/2024 - 17:06:57"
        },
        {
            "song_name": "bahia nights",
            "artists": [
                "moodsinger"
            ],
            "album": "bahia nights",
            "played_at": "01/08/2024 - 17:04:41"
        },
        {
            "song_name": "same dream",
            "artists": [
                "sozin"
            ],
            "album": "same dream",
            "played_at": "01/08/2024 - 17:02:42"
        },
        {
            "song_name": "Sea Breeze",
            "artists": [
                "Shimon Hoshino"
            ],
            "album": "Sea Breeze",
            "played_at": "01/08/2024 - 17:00:26"
        },
        {
            "song_name": "Like a Mystery",
            "artists": [
                "Eneko Artola"
            ],
            "album": "Like a Mystery",
            "played_at": "01/08/2024 - 16:50:59"
        },
        {
            "song_name": "Sweetly",
            "artists": [
                "Honey",
                "Summer Vibes"
            ],
            "album": "Sweetly",
            "played_at": "01/08/2024 - 16:48:47"
        },
        {
            "song_name": "I Can't Stop",
            "artists": [
                "Daniel Glaven",
                "Will Church"
            ],
            "album": "I Can't Stop",
            "played_at": "01/08/2024 - 16:46:16"
        },
        {
            "song_name": "Love Me",
            "artists": [
                "Donner"
            ],
            "album": "Love Me",
            "played_at": "01/08/2024 - 16:44:10"
        },
        {
            "song_name": "Coming With You",
            "artists": [
                "Horizon Blue",
                "Felix Samuel"
            ],
            "album": "Coming With You",
            "played_at": "01/08/2024 - 16:42:02"
        },
        {
            "song_name": "Dreams",
            "artists": [
                "Kenn Colt",
                "Adam Pickard"
            ],
            "album": "BALANCE",
            "played_at": "01/08/2024 - 16:39:49"
        },
        {
            "song_name": "Covered By The Clouds",
            "artists": [
                "NSH"
            ],
            "album": "Covered By The Clouds",
            "played_at": "01/08/2024 - 16:36:32"
        },
        {
            "song_name": "Talking To Myself",
            "artists": [
                "Namic",
                "Meynberg"
            ],
            "album": "Talking To Myself",
            "played_at": "01/08/2024 - 16:33:19"
        },
        {
            "song_name": "King",
            "artists": [
                "TWOPILOTS"
            ],
            "album": "King",
            "played_at": "01/08/2024 - 16:31:14"
        },
        {
            "song_name": "high love",
            "artists": [
                "rayn",
                "cloudseven",
                "MELINA"
            ],
            "album": "high love",
            "played_at": "01/08/2024 - 16:27:50"
        },
        {
            "song_name": "17",
            "artists": [
                "Weisser Quiff"
            ],
            "album": "17",
            "played_at": "01/08/2024 - 16:25:23"
        },
        {
            "song_name": "Dollar Dream [Lucas Estrada Edit]",
            "artists": [
                "Lucas Estrada",
                "Couché",
                "Polar Notes",
                "Mentum"
            ],
            "album": "Dollar Dream [Lucas Estrada Edit]",
            "played_at": "01/08/2024 - 16:22:36"
        },
        {
            "song_name": "Hollywood",
            "artists": [
                "Natio",
                "Nina Carr"
            ],
            "album": "Hollywood",
            "played_at": "01/08/2024 - 16:20:04"
        },
        {
            "song_name": "Stop Us Now",
            "artists": [
                "NSH",
                "DT James"
            ],
            "album": "Stop Us Now",
            "played_at": "01/08/2024 - 16:17:39"
        },
        {
            "song_name": "Sunset Lovers",
            "artists": [
                "Thierry Von Der Warth",
                "Horizon Blue",
                "Carston"
            ],
            "album": "Sunset Lovers",
            "played_at": "01/08/2024 - 16:15:31"
        },
        {
            "song_name": "Cool Kids",
            "artists": [
                "Toby Rose",
                "TWOPILOTS"
            ],
            "album": "Cool Kids",
            "played_at": "01/08/2024 - 16:12:41"
        },
        {
            "song_name": "In Too Deep",
            "artists": [
                "WEEKLESS",
                "WEDONT",
                "ROBINS"
            ],
            "album": "In Too Deep",
            "played_at": "01/08/2024 - 16:10:14"
        },
        {
            "song_name": "Over You",
            "artists": [
                "Madism",
                "Philip Strand"
            ],
            "album": "Over You",
            "played_at": "01/08/2024 - 16:07:35"
        },
        {
            "song_name": "Moonlight",
            "artists": [
                "Thunder"
            ],
            "album": "Moonlight",
            "played_at": "01/08/2024 - 16:05:19"
        },
        {
            "song_name": "Fallin' In Love",
            "artists": [
                "Ruxolf",
                "Marphil"
            ],
            "album": "Fallin' In Love",
            "played_at": "01/08/2024 - 16:03:17"
        },
        {
            "song_name": "Fire in the Sky",
            "artists": [
                "Roman Müller",
                "Clay Pirinha"
            ],
            "album": "Fire in the Sky",
            "played_at": "01/08/2024 - 16:00:45"
        },
        {
            "song_name": "Sunbeams",
            "artists": [
                "NSH"
            ],
            "album": "Sunbeams",
            "played_at": "01/08/2024 - 15:57:55"
        },
        {
            "song_name": "Guy For That (Feat. Luke Combs)",
            "artists": [
                "Post Malone",
                "Luke Combs"
            ],
            "album": "Guy For That",
            "played_at": "01/08/2024 - 15:54:03"
        },
        {
            "song_name": "Ball W/O You - Instrumental",
            "artists": [
                "DJ Glacier"
            ],
            "album": "Ball W/O You (Instrumental)",
            "played_at": "01/08/2024 - 15:52:05"
        },
        {
            "song_name": "Solo - Sped Up + Instrumental",
            "artists": [
                "dopuu"
            ],
            "album": "Solo - Sped Up + Instrumental",
            "played_at": "01/08/2024 - 15:48:50"
        },
        {
            "song_name": "Dreams",
            "artists": [
                "DJ ZeeZee"
            ],
            "album": "Dreams",
            "played_at": "01/08/2024 - 15:44:46"
        },
        {
            "song_name": "Hate It Or Love It",
            "artists": [
                "The Game",
                "50 Cent"
            ],
            "album": "The Documentary",
            "played_at": "01/08/2024 - 18:10:12"
        },
        {
            "song_name": "Unforgettable",
            "artists": [
                "French Montana",
                "Swae Lee"
            ],
            "album": "Jungle Rules",
            "played_at": "01/08/2024 - 18:09:41"
        },
        {
            "song_name": "The Percocet & Stripper Joint",
            "artists": [
                "Future"
            ],
            "album": "DS2 (Deluxe)",
            "played_at": "01/08/2024 - 18:05:47"
        },
        {
            "song_name": "Ric Flair Drip (with Metro Boomin)",
            "artists": [
                "Offset",
                "Metro Boomin"
            ],
            "album": "Without Warning",
            "played_at": "01/08/2024 - 18:03:18"
        },
        {
            "song_name": "one of wun",
            "artists": [
                "Gunna"
            ],
            "album": "One of Wun",
            "played_at": "01/08/2024 - 18:00:26"
        },
        {
            "song_name": "Wish I Never Met You - Prison Tapes",
            "artists": [
                "Tory Lanez"
            ],
            "album": "Wish I Never Met You (Prison Tapes)",
            "played_at": "01/08/2024 - 17:58:02"
        },
        {
            "song_name": "Self Care",
            "artists": [
                "Mac Miller"
            ],
            "album": "Swimming",
            "played_at": "01/08/2024 - 17:54:17"
        },
        {
            "song_name": "A Keeper",
            "artists": [
                "Drake"
            ],
            "album": "Honestly, Nevermind",
            "played_at": "01/08/2024 - 17:48:32"
        },
        {
            "song_name": "Sudden Change",
            "artists": [
                "Lonely Joyman"
            ],
            "album": "A Bit of Colour",
            "played_at": "01/08/2024 - 17:45:38"
        },
        {
            "song_name": "Dad's Typewriter Feels",
            "artists": [
                "Looper Boy"
            ],
            "album": "Once Again",
            "played_at": "01/08/2024 - 17:43:52"
        },
        {
            "song_name": "Dad's Typewriter Feels",
            "artists": [
                "Looper Boy"
            ],
            "album": "Once Again",
            "played_at": "01/08/2024 - 17:41:41"
        },
        {
            "song_name": "Boulevard",
            "artists": [
                "Jasper Nyx"
            ],
            "album": "Boulevard",
            "played_at": "01/08/2024 - 17:29:11"
        },
        {
            "song_name": "pawsitive",
            "artists": [
                "misty tapes"
            ],
            "album": "pawsitive",
            "played_at": "01/08/2024 - 17:26:26"
        },
        {
            "song_name": "Phunsmoke",
            "artists": [
                "LOFI FRAN"
            ],
            "album": "Phunsmoke",
            "played_at": "01/08/2024 - 17:24:15"
        },
        {
            "song_name": "Cruising",
            "artists": [
                "Lghtr"
            ],
            "album": "Cruising",
            "played_at": "01/08/2024 - 17:22:28"
        },
        {
            "song_name": "winter balloon",
            "artists": [
                "Ponzi Skeemz"
            ],
            "album": "winter balloon",
            "played_at": "01/08/2024 - 17:20:25"
        },
        {
            "song_name": "In Comparison With",
            "artists": [
                "State Artefact"
            ],
            "album": "In Comparison With",
            "played_at": "01/08/2024 - 17:18:19"
        },
        {
            "song_name": "Kalamos",
            "artists": [
                "Drips Zacheer",
                "Soulvibe Cuts"
            ],
            "album": "Kalamos",
            "played_at": "01/08/2024 - 17:15:03"
        },
        {
            "song_name": "Chewy",
            "artists": [
                "sloh rou",
                "ron quixote"
            ],
            "album": "Chewy",
            "played_at": "01/08/2024 - 17:13:01"
        },
        {
            "song_name": "Sundew",
            "artists": [
                "Sátyr",
                "Otaam",
                "Dubillard",
                "Enluv"
            ],
            "album": "Sundew",
            "played_at": "01/08/2024 - 17:10:38"
        },
        {
            "song_name": "Early Birds",
            "artists": [
                "FloFilz",
                "HNNY"
            ],
            "album": "Early Birds",
            "played_at": "01/08/2024 - 17:06:57"
        },
        {
            "song_name": "bahia nights",
            "artists": [
                "moodsinger"
            ],
            "album": "bahia nights",
            "played_at": "01/08/2024 - 17:04:41"
        },
        {
            "song_name": "same dream",
            "artists": [
                "sozin"
            ],
            "album": "same dream",
            "played_at": "01/08/2024 - 17:02:42"
        },
        {
            "song_name": "Sea Breeze",
            "artists": [
                "Shimon Hoshino"
            ],
            "album": "Sea Breeze",
            "played_at": "01/08/2024 - 17:00:26"
        },
        {
            "song_name": "Like a Mystery",
            "artists": [
                "Eneko Artola"
            ],
            "album": "Like a Mystery",
            "played_at": "01/08/2024 - 16:50:59"
        },
        {
            "song_name": "Sweetly",
            "artists": [
                "Honey",
                "Summer Vibes"
            ],
            "album": "Sweetly",
            "played_at": "01/08/2024 - 16:48:47"
        },
        {
            "song_name": "I Can't Stop",
            "artists": [
                "Daniel Glaven",
                "Will Church"
            ],
            "album": "I Can't Stop",
            "played_at": "01/08/2024 - 16:46:16"
        },
        {
            "song_name": "Love Me",
            "artists": [
                "Donner"
            ],
            "album": "Love Me",
            "played_at": "01/08/2024 - 16:44:10"
        },
        {
            "song_name": "Coming With You",
            "artists": [
                "Horizon Blue",
                "Felix Samuel"
            ],
            "album": "Coming With You",
            "played_at": "01/08/2024 - 16:42:02"
        },
        {
            "song_name": "Dreams",
            "artists": [
                "Kenn Colt",
                "Adam Pickard"
            ],
            "album": "BALANCE",
            "played_at": "01/08/2024 - 16:39:49"
        },
        {
            "song_name": "Covered By The Clouds",
            "artists": [
                "NSH"
            ],
            "album": "Covered By The Clouds",
            "played_at": "01/08/2024 - 16:36:32"
        },
        {
            "song_name": "Talking To Myself",
            "artists": [
                "Namic",
                "Meynberg"
            ],
            "album": "Talking To Myself",
            "played_at": "01/08/2024 - 16:33:19"
        },
        {
            "song_name": "King",
            "artists": [
                "TWOPILOTS"
            ],
            "album": "King",
            "played_at": "01/08/2024 - 16:31:14"
        },
        {
            "song_name": "high love",
            "artists": [
                "rayn",
                "cloudseven",
                "MELINA"
            ],
            "album": "high love",
            "played_at": "01/08/2024 - 16:27:50"
        },
        {
            "song_name": "17",
            "artists": [
                "Weisser Quiff"
            ],
            "album": "17",
            "played_at": "01/08/2024 - 16:25:23"
        },
        {
            "song_name": "Dollar Dream [Lucas Estrada Edit]",
            "artists": [
                "Lucas Estrada",
                "Couché",
                "Polar Notes",
                "Mentum"
            ],
            "album": "Dollar Dream [Lucas Estrada Edit]",
            "played_at": "01/08/2024 - 16:22:36"
        },
        {
            "song_name": "Hollywood",
            "artists": [
                "Natio",
                "Nina Carr"
            ],
            "album": "Hollywood",
            "played_at": "01/08/2024 - 16:20:04"
        },
        {
            "song_name": "Stop Us Now",
            "artists": [
                "NSH",
                "DT James"
            ],
            "album": "Stop Us Now",
            "played_at": "01/08/2024 - 16:17:39"
        },
        {
            "song_name": "Sunset Lovers",
            "artists": [
                "Thierry Von Der Warth",
                "Horizon Blue",
                "Carston"
            ],
            "album": "Sunset Lovers",
            "played_at": "01/08/2024 - 16:15:31"
        },
        {
            "song_name": "Cool Kids",
            "artists": [
                "Toby Rose",
                "TWOPILOTS"
            ],
            "album": "Cool Kids",
            "played_at": "01/08/2024 - 16:12:41"
        },
        {
            "song_name": "In Too Deep",
            "artists": [
                "WEEKLESS",
                "WEDONT",
                "ROBINS"
            ],
            "album": "In Too Deep",
            "played_at": "01/08/2024 - 16:10:14"
        },
        {
            "song_name": "Over You",
            "artists": [
                "Madism",
                "Philip Strand"
            ],
            "album": "Over You",
            "played_at": "01/08/2024 - 16:07:35"
        },
        {
            "song_name": "Moonlight",
            "artists": [
                "Thunder"
            ],
            "album": "Moonlight",
            "played_at": "01/08/2024 - 16:05:19"
        },
        {
            "song_name": "Fallin' In Love",
            "artists": [
                "Ruxolf",
                "Marphil"
            ],
            "album": "Fallin' In Love",
            "played_at": "01/08/2024 - 16:03:17"
        },
        {
            "song_name": "Fire in the Sky",
            "artists": [
                "Roman Müller",
                "Clay Pirinha"
            ],
            "album": "Fire in the Sky",
            "played_at": "01/08/2024 - 16:00:45"
        },
        {
            "song_name": "Sunbeams",
            "artists": [
                "NSH"
            ],
            "album": "Sunbeams",
            "played_at": "01/08/2024 - 15:57:55"
        },
        {
            "song_name": "Guy For That (Feat. Luke Combs)",
            "artists": [
                "Post Malone",
                "Luke Combs"
            ],
            "album": "Guy For That",
            "played_at": "01/08/2024 - 15:54:03"
        },
        {
            "song_name": "Ball W/O You - Instrumental",
            "artists": [
                "DJ Glacier"
            ],
            "album": "Ball W/O You (Instrumental)",
            "played_at": "01/08/2024 - 15:52:05"
        },
        {
            "song_name": "Solo - Sped Up + Instrumental",
            "artists": [
                "dopuu"
            ],
            "album": "Solo - Sped Up + Instrumental",
            "played_at": "01/08/2024 - 15:48:50"
        },
        {
            "song_name": "Dreams",
            "artists": [
                "DJ ZeeZee"
            ],
            "album": "Dreams",
            "played_at": "01/08/2024 - 15:44:46"
        }
    ]
}